{
    "$schema": "http://json-schema.org/schema#",
    "$id": "https://w3id.org/demeter/agri/agriCrop?_profile=jsonschema",
    "type": "object",
    "properties": {
        "iso19150-2:Datatype": {
            "type": "object",
            "properties": {},
            "required": []
        },
        "foodie:CropType": {
            "type": "object",
            "properties": {
                "foodie:code": {
                    "type": "string"
                },
                "foodie:species": {
                    "type": "string"
                },
                "foodie:family": {
                    "type": "string"
                },
                "foodie:genus": {
                    "type": "string"
                },
                "foodie:variety": {
                    "type": "string"
                },
                "foodie:description": {
                    "type": "string"
                },
                "foodie:notes": {
                    "type": "string"
                }
            },
            "required": []
        },
        "foodie:ProductionType": {
            "type": "object",
            "properties": {
                "foodie:variety": {
                    "type": "string"
                },
                "foodie:productionAmount": {
                    "type": "string"
                },
                "foodie:productionDate": {
                    "type": "string"
                }
            },
            "required": [
                "foodie:variety",
                "foodie:productionDate"
            ]
        },
        "iso19150-2:FeatureType": {
            "type": "object",
            "properties": {},
            "required": []
        },
        "iso19109:AnyFeature": {
            "type": "object",
            "properties": {},
            "required": []
        },
        "geo:Feature": {
            "type": "object",
            "properties": {
                "geo:hasGeometry": {
                    "type": "array",
                    "items": {
                        "type": "string"
                    }
                }
            },
            "required": []
        },
        "geo:SpatialObject": {
            "type": "object",
            "properties": {
                "geo:sfContains": {
                    "type": "array",
                    "items": {
                        "type": "string"
                    }
                },
                "geo:sfWithin": {
                    "type": "array",
                    "items": {
                        "type": "string"
                    }
                }
            },
            "required": []
        },
        "foodie:CropSpecies": {
            "type": "object",
            "properties": {
                "foodie:cropArea": {
                    "type": "array",
                    "items": {
                        "type": "string"
                    }
                },
                "common:validTo": {
                    "type": "string"
                },
                "prov:generatedAtTime": {
                    "type": "string"
                },
                "foodie:cropSpecies": {
                    "type": "string"
                },
                "prov:invalidatedAtTime": {
                    "type": "string"
                },
                "common:validFrom": {
                    "type": "string"
                }
            },
            "required": [
                "foodie:cropArea",
                "prov:generatedAtTime",
                "foodie:cropSpecies",
                "common:validFrom"
            ]
        },
        "saref:FeatureOfInterest": {
            "type": "object",
            "properties": {},
            "required": []
        },
        "saref4agri:Crop": {
            "type": "object",
            "properties": {
                "saref4agri:hasHarvestDate": {
                    "type": "array",
                    "items": {
                        "type": "string"
                    }
                },
                "saref4agri:hasPlantDate": {
                    "type": "array",
                    "items": {
                        "type": "string"
                    }
                },
                "obo:TAXRANK_1000000": {
                    "type": "array",
                    "items": {
                        "type": "string"
                    }
                }
            },
            "required": []
        },
        "fiware:AgriCrop": {
            "type": "object",
            "properties": {},
            "required": []
        }
    }
}