{
    "$schema": "http://json-schema.org/schema#",
    "$id": "https://w3id.org/demeter/agri/agriFeature?_profile=jsonschema",
    "type": "object",
    "properties": {
        "sf:PolyhedralSurface": {
            "type": "object",
            "properties": {},
            "required": []
        },
        "sf:Surface": {
            "type": "object",
            "properties": {},
            "required": []
        },
        "sf:Geometry": {
            "type": "object",
            "properties": {},
            "required": []
        },
        "geo:Geometry": {
            "type": "object",
            "properties": {
                "geo:hasSerialization": {
                    "type": "array",
                    "items": {
                        "type": "string"
                    }
                },
                "geo:dimension": {
                    "type": "array",
                    "items": {
                        "type": "string"
                    }
                },
                "geo:asWKT": {
                    "type": "array",
                    "items": {
                        "type": "string"
                    }
                },
                "geo:isEmpty": {
                    "type": "array",
                    "items": {
                        "type": "string"
                    }
                },
                "geo:isSimple": {
                    "type": "array",
                    "items": {
                        "type": "string"
                    }
                },
                "geo:asGML": {
                    "type": "array",
                    "items": {
                        "type": "string"
                    }
                },
                "geo:coordinateDimension": {
                    "type": "array",
                    "items": {
                        "type": "string"
                    }
                },
                "geo:spatialDimension": {
                    "type": "array",
                    "items": {
                        "type": "string"
                    }
                }
            },
            "required": []
        },
        "geo:SpatialObject": {
            "type": "object",
            "properties": {
                "geo:ehCoveredBy": {
                    "type": "array",
                    "items": {
                        "type": "string"
                    }
                },
                "geo:ehOverlap": {
                    "type": "array",
                    "items": {
                        "type": "string"
                    }
                },
                "geo:rcc8ntpp": {
                    "type": "array",
                    "items": {
                        "type": "string"
                    }
                },
                "geo:sfOverlaps": {
                    "type": "array",
                    "items": {
                        "type": "string"
                    }
                },
                "geo:rcc8eq": {
                    "type": "array",
                    "items": {
                        "type": "string"
                    }
                },
                "geo:rcc8ec": {
                    "type": "array",
                    "items": {
                        "type": "string"
                    }
                },
                "geo:rcc8tppi": {
                    "type": "array",
                    "items": {
                        "type": "string"
                    }
                },
                "geo:ehCovers": {
                    "type": "array",
                    "items": {
                        "type": "string"
                    }
                },
                "geo:sfEquals": {
                    "type": "array",
                    "items": {
                        "type": "string"
                    }
                },
                "geo:rcc8ntppi": {
                    "type": "array",
                    "items": {
                        "type": "string"
                    }
                },
                "geo:rcc8po": {
                    "type": "array",
                    "items": {
                        "type": "string"
                    }
                },
                "geo:sfDisjoint": {
                    "type": "array",
                    "items": {
                        "type": "string"
                    }
                },
                "geo:sfTouches": {
                    "type": "array",
                    "items": {
                        "type": "string"
                    }
                },
                "geo:sfWithin": {
                    "type": "array",
                    "items": {
                        "type": "string"
                    }
                },
                "geo:ehMeet": {
                    "type": "array",
                    "items": {
                        "type": "string"
                    }
                },
                "geo:ehInside": {
                    "type": "array",
                    "items": {
                        "type": "string"
                    }
                },
                "geo:sfCrosses": {
                    "type": "array",
                    "items": {
                        "type": "string"
                    }
                },
                "geo:rcc8dc": {
                    "type": "array",
                    "items": {
                        "type": "string"
                    }
                },
                "geo:rcc8tpp": {
                    "type": "array",
                    "items": {
                        "type": "string"
                    }
                },
                "geo:ehContains": {
                    "type": "array",
                    "items": {
                        "type": "string"
                    }
                },
                "geo:ehDisjoint": {
                    "type": "array",
                    "items": {
                        "type": "string"
                    }
                },
                "geo:ehEquals": {
                    "type": "array",
                    "items": {
                        "type": "string"
                    }
                },
                "geo:sfIntersects": {
                    "type": "array",
                    "items": {
                        "type": "string"
                    }
                },
                "geo:sfContains": {
                    "type": "array",
                    "items": {
                        "type": "string"
                    }
                },
                "geo:hasGeometry": {
                    "type": "array",
                    "items": {
                        "type": "string"
                    }
                },
                "wgs84_pos:location": {
                    "type": "array",
                    "items": {
                        "type": "string"
                    }
                }
            },
            "required": []
        },
        "sf:TIN": {
            "type": "object",
            "properties": {},
            "required": []
        },
        "sf:GeometryCollection": {
            "type": "object",
            "properties": {},
            "required": []
        },
        "sf:MultiPoint": {
            "type": "object",
            "properties": {},
            "required": []
        },
        "sf:MultiSurface": {
            "type": "object",
            "properties": {},
            "required": []
        },
        "sf:MultiPolygon": {
            "type": "object",
            "properties": {},
            "required": []
        },
        "sf:Polygon": {
            "type": "object",
            "properties": {},
            "required": []
        },
        "sf:Curve": {
            "type": "object",
            "properties": {},
            "required": []
        },
        "sf:LineString": {
            "type": "object",
            "properties": {},
            "required": []
        },
        "sf:Point": {
            "type": "object",
            "properties": {},
            "required": []
        },
        "sf:MultiCurve": {
            "type": "object",
            "properties": {},
            "required": []
        },
        "sf:MultiLineString": {
            "type": "object",
            "properties": {},
            "required": []
        },
        "sf:Line": {
            "type": "object",
            "properties": {},
            "required": []
        },
        "sf:Triangle": {
            "type": "object",
            "properties": {},
            "required": []
        },
        "sf:LinearRing": {
            "type": "object",
            "properties": {},
            "required": []
        },
        "wgs84_pos:SpatialThing": {
            "type": "object",
            "properties": {
                "wgs84_pos:lat": {
                    "type": "array",
                    "items": {
                        "type": "string"
                    }
                },
                "wgs84_pos:alt": {
                    "type": "array",
                    "items": {
                        "type": "string"
                    }
                },
                "wgs84_pos:long": {
                    "type": "array",
                    "items": {
                        "type": "string"
                    }
                }
            },
            "required": []
        },
        "wgs84_pos:Point": {
            "type": "object",
            "properties": {},
            "required": []
        },
        "geo:Feature": {
            "type": "object",
            "properties": {
                "geo:defaultGeometry": {
                    "type": "array",
                    "items": {
                        "type": "string"
                    }
                },
                "geo:hasGeometry": {
                    "type": "array",
                    "items": {
                        "type": "string"
                    }
                }
            },
            "required": []
        },
        "iso19109:AnyFeature": {
            "type": "object",
            "properties": {},
            "required": []
        },
        "iso19150-2:FeatureType": {
            "type": "object",
            "properties": {},
            "required": []
        },
        "foodie:Plot": {
            "type": "object",
            "properties": {
                "prov:generatedAtTime": {
                    "type": "string"
                },
                "foodie:code": {
                    "type": "string"
                },
                "geo:hasGeometry": {
                    "type": "array",
                    "items": {
                        "type": "string"
                    }
                },
                "common:validFrom": {
                    "type": "string"
                },
                "common:validTo": {
                    "type": "string"
                },
                "prov:invalidatedAtTime": {
                    "type": "string"
                },
                "foodie:description": {
                    "type": "string"
                },
                "foodie:originType": {
                    "type": "string"
                }
            },
            "required": [
                "prov:generatedAtTime",
                "foodie:code",
                "geo:hasGeometry",
                "common:validFrom",
                "foodie:originType"
            ]
        },
        "iso19150-2:Codelist": {
            "type": "object",
            "properties": {},
            "required": []
        },
        "skos:Concept": {
            "type": "object",
            "properties": {},
            "required": []
        },
        "foodie:OriginTypeValue": {
            "type": "object",
            "properties": {},
            "required": []
        },
        "foodie:ManagementZone": {
            "type": "object",
            "properties": {
                "common:validTo": {
                    "type": "string"
                },
                "prov:generatedAtTime": {
                    "type": "string"
                },
                "foodie:code": {
                    "type": "string"
                },
                "foodie:notes": {
                    "type": "string"
                },
                "prov:invalidatedAtTime": {
                    "type": "string"
                },
                "geo:hasGeometry": {
                    "type": "array",
                    "items": {
                        "type": "string"
                    }
                },
                "common:validFrom": {
                    "type": "string"
                }
            },
            "required": [
                "prov:generatedAtTime",
                "foodie:code",
                "foodie:notes",
                "geo:hasGeometry"
            ]
        },
        "act-inspire:ActivityComplex": {
            "type": "object",
            "properties": {},
            "required": []
        },
        "af-inspire:Holding": {
            "type": "object",
            "properties": {
                "foodie:userId": {
                    "type": "string"
                },
                "geo:hasGeometry": {
                    "type": "string"
                },
                "af-inspire:contains": {
                    "type": "array",
                    "items": {
                        "type": "string"
                    }
                }
            },
            "required": [
                "foodie:userId",
                "geo:hasGeometry",
                "af-inspire:contains"
            ]
        },
        "af-inspire:Site": {
            "type": "object",
            "properties": {
                "common:validTo": {
                    "type": "string"
                },
                "prov:generatedAtTime": {
                    "type": "string"
                },
                "common:validFrom": {
                    "type": "string"
                },
                "foodie:containsPlot": {
                    "type": "array",
                    "items": {
                        "type": "string"
                    }
                },
                "foodie:code": {
                    "type": "string"
                },
                "geo:hasGeometry": {
                    "type": "string"
                },
                "prov:invalidatedAtTime": {
                    "type": "string"
                },
                "af-inspire:activity": {
                    "type": "array",
                    "items": {
                        "type": "string"
                    }
                }
            },
            "required": [
                "prov:generatedAtTime",
                "common:validFrom",
                "foodie:containsPlot",
                "foodie:code",
                "geo:hasGeometry",
                "af-inspire:activity"
            ]
        },
        "fiware:AgriParcel": {
            "type": "object",
            "properties": {},
            "required": []
        },
        "fiware:AgriGreenhouse": {
            "type": "object",
            "properties": {},
            "required": []
        },
        "fiware:AgriFarm": {
            "type": "object",
            "properties": {},
            "required": []
        },
        "act-inspire:EconomicActivityNACEValue": {
            "type": "object",
            "properties": {},
            "required": []
        },
        "saref4agri:Parcel": {
            "type": "object",
            "properties": {
                "saref4agri:contains": {
                    "type": "array",
                    "items": {
                        "type": "string"
                    }
                },
                "saref4agri:hasName": {
                    "type": "array",
                    "items": {
                        "type": "string"
                    }
                }
            },
            "required": []
        },
        "saref4agri:BuildingSpace": {
            "type": "object",
            "properties": {},
            "required": []
        },
        "saref4agri:Farm": {
            "type": "object",
            "properties": {
                "saref4agri:contains": {
                    "type": "array",
                    "items": {
                        "type": "string"
                    }
                },
                "saref4agri:hasName": {
                    "type": "string"
                }
            },
            "required": []
        },
        "saref4agri:Building": {
            "type": "object",
            "properties": {
                "saref4agri:contains": {
                    "type": "array",
                    "items": {
                        "type": "string"
                    }
                },
                "saref4agri:hasName": {
                    "type": "string"
                }
            },
            "required": []
        }
    }
}